<setup>
	<block title="Set the global log level" endpoint="admin/alert_actions" entity="triggr">
		<text>Set the global logging level for this app. Possibel values are FATAL, ERROR, WARN, INFO, or DEBUG.</text>
		<input field="param.log_level">
			<label>Log Level</label>
			<type>text</type>
		</input>
	</block>
	<block title="Enable certificate validation" endpoint="admin/alert_actions" entity="triggr">
		<text>Set whether to validate the local Splunk server's certificate when making REST API calls. If Splunk's default self signed certificates are used, set this value to 0.</text>
		<input field="param.cert_validation">
			<label>Certificate Validation</label>
			<type>text</type>
		</input>
	</block>
</setup>